gdbundle_gdb_callgrind/__init__.py
gdbundle_gdb_callgrind/gdb_loader.py
gdbundle_gdb_callgrind/scripts/gdb_callgrind.py
gdbundle_gdb_callgrind-0.1.dist-info/LICENSE
gdbundle_gdb_callgrind-0.1.dist-info/WHEEL
gdbundle_gdb_callgrind-0.1.dist-info/METADATA
gdbundle_gdb_callgrind-0.1.dist-info/RECORD
