Metadata-Version: 2.1
Name: gdbundle-gdb-callgrind
Version: 0.1
Summary: 
License: Apache 2.0
Author: Josh Pieper
Author-email: jjp@pobox.com
Requires-Python: >=3.0,<4.0
Classifier: Development Status :: 2 - Pre-Alpha
Classifier: Environment :: Plugins
Classifier: Intended Audience :: Developers
Classifier: License :: OSI Approved :: Apache Software License
Classifier: License :: Other/Proprietary License
Classifier: Operating System :: OS Independent
Classifier: Programming Language :: Python :: 3
Classifier: Topic :: Software Development :: Debuggers
Classifier: Topic :: Software Development :: Libraries :: Python Modules
Requires-Dist: gdbundle (>=0.0.3,<0.1.0)
